Workbook

Sheet Assumptions
A1: Input | B1: Free | C1: Pro | D1: Premium
A2: Price ($/mo) | B2: 0 | C2: 29 | D2: 79
A3: Hosting ($/user/mo) | B3: 0.6 | C3: 3.2 | D3: 6.5
A4: Support ($/user/mo) | B4: 0.1 | C4: 1.5 | D4: 4
A5: Monthly churn | B5: 0.15 | C5: 0.06 | D5: 0.04
A6: CAC ($) | B6: 12 | C6: 85 | D6: 160
A8: Stripe % | B8: 0.029
A9: Stripe fixed ($) | B9: 0.3

Sheet Unit Economics
A1: Output | B1: Free | C1: Pro | D1: Premium
A2: Payment fee | B2: =IF(Assumptions!B2=0,0,Assumptions!B2*Assumptions!B8+Assumptions!B9) -> 0 | C2: =Assumptions!C2*0.029+0.3 -> 1.141 | D2: =Assumptions!C2*0.029+0.3 -> 1.141
A3: Gross margin | B3: =Assumptions!B2-Assumptions!B3-Assumptions!B4-B2 -> -0.7 | C3: =Assumptions!C2-Assumptions!C3-Assumptions!C4-C2 -> 23.159 | D3: =Assumptions!D2-Assumptions!D3-Assumptions!D4-D2 -> 67.359
A4: Margin % | B4: ="n/a" -> n/a | C4: =C3/Assumptions!C2 -> 0.79858621 | D4: =D3/Assumptions!D2 -> 0.85264557
A5: LTV | B5: =B3/Assumptions!B5 -> -4.6666667 | C5: =C3/Assumptions!C5 -> 385.98333 | D5: =D3/Assumptions!D5 -> 1683.975
A6: CAC payback (mo) | B6: ="n/a" -> n/a | C6: =Assumptions!C6/C3 -> 3.6702794 | D6: =Assumptions!D6/D3 -> 2.3753322
A7: LTV:CAC | B7: =B5/Assumptions!B6 -> -0.38888889 | C7: =C5/Assumptions!C6 -> 4.5409804 | D7: =D5/Assumptions!D6 -> 10.524844

Sheet Scenario
A1: High-churn scenario for Pro (what-if) | B1: Value
A2: Price | B2: =Assumptions!C2 -> 29
A3: Gross margin | B3: ='Unit Economics'!C3 -> 23.159
A4: Monthly churn (typed by analyst) | B4: 6
A5: LTV | B5: =B3/B4 -> 3.8598333

Sheet Read Me
A1: GrowVest unit economics model, v1 (inherited artifact).
A2: Yellow cells are inputs. All figures are per user per month.
A3: Prices are GrowVest's published tiers; costs, churn and CAC are simulated.
A4: KNOWN DEFECTS (Assignment 3.2 audit): R-01 Premium fee uses Pro price;
A5: R-02 Stripe fee hard-coded in formulas; R-03 churn accepted as whole percent.
